capsolver_python/__init__.py
capsolver_python/antiakamai_bmp.py
capsolver_python/antikasada.py
capsolver_python/capsolver.py
capsolver_python/datadome_slider.py
capsolver_python/fun_captcha.py
capsolver_python/funcaptcha_classification.py
capsolver_python/gee_test.py
capsolver_python/h_captcha.py
capsolver_python/hcaptcha_classification.py
capsolver_python/image_to_text.py
capsolver_python/proxy.py
capsolver_python/recaptcha_v2.py
capsolver_python/recaptcha_v2_enterprise.py
capsolver_python/recaptcha_v3.py
capsolver_python/request_type.py
capsolver_python/useragent.py
capsolver_python/utils.py
capsolver_python-1.0.dist-info/LICENSE
capsolver_python-1.0.dist-info/METADATA
capsolver_python-1.0.dist-info/WHEEL
capsolver_python-1.0.dist-info/top_level.txt
capsolver_python-1.0.dist-info/RECORD
